sphinx_scylla_theme/__init__.py
sphinx_scylla_theme/extensions/_utils.py
sphinx_scylla_theme/extensions/panel-box.py
sphinx_scylla_theme/extensions/topic-box.py
sphinx_scylla_theme/layout.html
sphinx_scylla_theme/searchbox.html
sphinx_scylla_theme/side-nav.html
sphinx_scylla_theme/static/app.js
sphinx_scylla_theme/static/css/doc/doc.css
sphinx_scylla_theme/static/css/doc/ext/sphinx-tab-box.css
sphinx_scylla_theme/static/css/doc/ext/topic-box.css
sphinx_scylla_theme/static/css/doc/main.css
sphinx_scylla_theme/static/css/foundation.css
sphinx_scylla_theme/static/css/foundation.min.css
sphinx_scylla_theme/static/css/site.css
sphinx_scylla_theme/static/expertrec.js
sphinx_scylla_theme/static/fonts/scylla.eot
sphinx_scylla_theme/static/fonts/scylla.svg
sphinx_scylla_theme/static/fonts/scylla.ttf
sphinx_scylla_theme/static/fonts/scylla.woff
sphinx_scylla_theme/static/img/.gitkeep
sphinx_scylla_theme/static/img/arow.png
sphinx_scylla_theme/static/img/art-1.svg
sphinx_scylla_theme/static/img/art.png
sphinx_scylla_theme/static/img/art.svg
sphinx_scylla_theme/static/img/art_inner.svg
sphinx_scylla_theme/static/img/art_inner_2.svg
sphinx_scylla_theme/static/img/art_inner_3.svg
sphinx_scylla_theme/static/img/art_inner_4.svg
sphinx_scylla_theme/static/img/ec2_launch_capture.png
sphinx_scylla_theme/static/img/ec2_launch_capture.small.png
sphinx_scylla_theme/static/img/event_Icon.svg
sphinx_scylla_theme/static/img/favicon.ico
sphinx_scylla_theme/static/img/logo-scylla-min.svg
sphinx_scylla_theme/static/img/logo-scylla.svg
sphinx_scylla_theme/static/img/logo.png
sphinx_scylla_theme/static/img/logo.svg
sphinx_scylla_theme/static/img/logo_w.svg
sphinx_scylla_theme/static/img/mascot_1.png
sphinx_scylla_theme/static/img/mascot_2.png
sphinx_scylla_theme/static/img/mascot_3.png
sphinx_scylla_theme/static/img/scylla-writer.svg
sphinx_scylla_theme/static/img/scylla_favicon.ico
sphinx_scylla_theme/static/img/vertigo.jpg
sphinx_scylla_theme/static/js/foundation/foundation.abide.js
sphinx_scylla_theme-0.1.0.dist-info/LICENSE
sphinx_scylla_theme-0.1.0.dist-info/WHEEL
sphinx_scylla_theme-0.1.0.dist-info/METADATA
sphinx_scylla_theme-0.1.0.dist-info/RECORD
